cloud_socket/__init__.py
cloud_socket/app.py
cloud_socket/auth.py
cloud_socket/example.py
cloud_socket/logger.py
cloud_socket/registry.py
cloud_socket-0.0.1.dist-info/licenses/LICENSE
cloud_socket-0.0.1.dist-info/METADATA
cloud_socket-0.0.1.dist-info/WHEEL
cloud_socket-0.0.1.dist-info/top_level.txt
cloud_socket-0.0.1.dist-info/RECORD
