Metadata-Version: 2.4
Name: cloud-socket
Version: 0.0.1
Summary: Cloud Socket is a secure websocket application that uses AES-GCM encryption and is build on fastapi. This also allows you to have google cloud run server without cold starts as it always has an open connection
Home-page: 
Author: Daniel Olson
Author-email: daniel@orphos.cloud
Keywords: websocket,socket,encryption,secure
Classifier: Development Status :: 3 - Alpha
Classifier: Intended Audience :: Developers
Classifier: License :: OSI Approved :: MIT License
Classifier: Operating System :: OS Independent
Classifier: Programming Language :: Python :: 3
Classifier: Programming Language :: Python :: 3.10
Classifier: Programming Language :: Python :: 3.11
Classifier: Programming Language :: Python :: 3.12
Requires-Python: >=3.10
License-File: LICENSE
Requires-Dist: cryptography
Requires-Dist: fastapi[uvicorn]
Requires-Dist: uvicorn
Dynamic: author
Dynamic: author-email
Dynamic: classifier
Dynamic: description
Dynamic: description-content-type
Dynamic: keywords
Dynamic: license-file
Dynamic: requires-dist
Dynamic: requires-python
Dynamic: summary
